{"time":"October 27, 11:05 pm","ts":1666892146,"status":200,"resp_time":3.126871}
{"time":"October 27, 11:21 pm","ts":1666893110,"status":200,"resp_time":3.317819}
{"time":"October 27, 11:57 pm","ts":1666895228,"status":200,"resp_time":3.027432}
{"time":"October 28, 12:24 am","ts":1666896878,"status":200,"resp_time":2.901581}
{"time":"October 28, 12:46 am","ts":1666898169,"status":200,"resp_time":3.585224}
{"time":"October 28, 1:00 am","ts":1666899032,"status":200,"resp_time":3.022346}
{"time":"October 28, 1:15 am","ts":1666899930,"status":200,"resp_time":3.149253}
{"time":"October 28, 1:26 am","ts":1666900560,"status":200,"resp_time":2.903784}
{"time":"October 28, 1:52 am","ts":1666902133,"status":200,"resp_time":3.144783}
{"time":"October 28, 2:13 am","ts":1666903383,"status":200,"resp_time":3.346806}
{"time":"October 28, 2:25 am","ts":1666904143,"status":200,"resp_time":3.266814}
{"time":"October 28, 2:47 am","ts":1666905445,"status":200,"resp_time":2.818203}
{"time":"October 28, 3:04 am","ts":1666906492,"status":200,"resp_time":3.015118}
{"time":"October 28, 3:17 am","ts":1666907268,"status":200,"resp_time":3.380344}
{"time":"October 28, 3:28 am","ts":1666907882,"status":200,"resp_time":2.960627}
{"time":"October 28, 3:55 am","ts":1666909516,"status":200,"resp_time":3.058498}
{"time":"October 28, 4:12 am","ts":1666910565,"status":200,"resp_time":2.847906}
{"time":"October 28, 4:25 am","ts":1666911349,"status":200,"resp_time":3.151312}
{"time":"October 28, 4:54 am","ts":1666913087,"status":200,"resp_time":3.147904}
{"time":"October 28, 5:16 am","ts":1666914365,"status":200,"resp_time":3.266016}
{"time":"October 28, 5:27 am","ts":1666915028,"status":200,"resp_time":3.0094}
{"time":"October 28, 7:53 am","ts":1666923824,"status":200,"resp_time":2.97671}
{"time":"October 28, 9:24 am","ts":1666929246,"status":200,"resp_time":3.237111}
{"time":"October 28, 10:16 am","ts":1666932416,"status":200,"resp_time":3.067841}
{"time":"October 28, 10:48 am","ts":1666934336,"status":200,"resp_time":3.219739}
{"time":"October 28, 11:15 am","ts":1666935910,"status":200,"resp_time":3.31311}
{"time":"October 28, 11:26 am","ts":1666936606,"status":200,"resp_time":3.043981}
{"time":"October 28, 11:59 am","ts":1666938541,"status":200,"resp_time":3.082784}
{"time":"October 28, 12:23 pm","ts":1666940009,"status":200,"resp_time":3.160778}
{"time":"October 28, 12:46 pm","ts":1666941397,"status":200,"resp_time":4.174469}
{"time":"October 28, 1:02 pm","ts":1666942353,"status":200,"resp_time":3.044097}
{"time":"October 28, 1:15 pm","ts":1666943143,"status":200,"resp_time":2.96969}
{"time":"October 28, 1:26 pm","ts":1666943770,"status":200,"resp_time":2.968147}
{"time":"October 28, 2:01 pm","ts":1666945911,"status":200,"resp_time":2.898374}
{"time":"October 28, 2:27 pm","ts":1666947431,"status":200,"resp_time":3.13281}
{"time":"October 28, 2:55 pm","ts":1666949105,"status":200,"resp_time":2.862971}
{"time":"October 28, 3:13 pm","ts":1666950198,"status":200,"resp_time":2.94216}
{"time":"October 28, 3:25 pm","ts":1666950936,"status":200,"resp_time":3.051337}
{"time":"October 28, 3:51 pm","ts":1666952502,"status":200,"resp_time":3.215391}
{"time":"October 28, 4:14 pm","ts":1666953896,"status":200,"resp_time":3.037577}
{"time":"October 28, 4:25 pm","ts":1666954552,"status":200,"resp_time":3.302888}
{"time":"October 28, 4:47 pm","ts":1666955869,"status":200,"resp_time":3.248348}
{"time":"October 28, 5:03 pm","ts":1666956834,"status":200,"resp_time":2.816083}
{"time":"October 28, 5:15 pm","ts":1666957556,"status":200,"resp_time":3.183151}
{"time":"October 28, 5:26 pm","ts":1666958181,"status":200,"resp_time":3.915748}
{"time":"October 28, 6:18 pm","ts":1666961284,"status":200,"resp_time":3.196501}
{"time":"October 28, 7:09 pm","ts":1666964368,"status":200,"resp_time":3.566295}
{"time":"October 28, 7:44 pm","ts":1666966485,"status":200,"resp_time":3.188585}
{"time":"October 28, 8:10 pm","ts":1666968053,"status":200,"resp_time":3.56746}
{"time":"October 28, 8:25 pm","ts":1666968945,"status":200,"resp_time":3.39263}
{"time":"October 28, 8:51 pm","ts":1666970496,"status":200,"resp_time":2.910544}
{"time":"October 28, 9:16 pm","ts":1666971999,"status":200,"resp_time":4.327272}
{"time":"October 28, 9:27 pm","ts":1666972673,"status":200,"resp_time":3.11202}
{"time":"October 28, 10:04 pm","ts":1666974842,"status":200,"resp_time":2.784996}
{"time":"October 28, 10:31 pm","ts":1666976512,"status":200,"resp_time":3.244315}
{"time":"October 28, 11:03 pm","ts":1666978410,"status":200,"resp_time":3.02022}
{"time":"October 28, 11:20 pm","ts":1666979432,"status":200,"resp_time":3.300593}
{"time":"October 28, 11:53 pm","ts":1666981437,"status":200,"resp_time":2.881923}
{"time":"October 29, 12:18 am","ts":1666982912,"status":200,"resp_time":3.284488}
{"time":"October 29, 12:29 am","ts":1666983569,"status":200,"resp_time":2.752678}
{"time":"October 29, 12:51 am","ts":1666984862,"status":200,"resp_time":3.313957}
{"time":"October 29, 1:07 am","ts":1666985828,"status":200,"resp_time":3.835169}
{"time":"October 29, 1:17 am","ts":1666986458,"status":200,"resp_time":3.270632}
{"time":"October 29, 1:27 am","ts":1666987077,"status":200,"resp_time":3.271766}
{"time":"October 29, 1:58 am","ts":1666988903,"status":200,"resp_time":3.289192}
{"time":"October 29, 2:16 am","ts":1666989979,"status":200,"resp_time":3.209814}
{"time":"October 29, 2:26 am","ts":1666990597,"status":200,"resp_time":3.456011}
{"time":"October 29, 2:49 am","ts":1666991989,"status":200,"resp_time":2.969678}
{"time":"October 29, 3:06 am","ts":1666992977,"status":200,"resp_time":2.143207}
{"time":"October 29, 3:18 am","ts":1666993705,"status":200,"resp_time":3.229408}
{"time":"October 29, 3:28 am","ts":1666994319,"status":200,"resp_time":3.06891}
{"time":"October 29, 3:56 am","ts":1666995977,"status":200,"resp_time":3.016626}
{"time":"October 29, 4:14 am","ts":1666997043,"status":200,"resp_time":3.142606}
{"time":"October 29, 4:25 am","ts":1666997729,"status":200,"resp_time":3.432023}
{"time":"October 29, 4:52 am","ts":1666999345,"status":200,"resp_time":3.315796}
{"time":"October 29, 5:15 am","ts":1667000703,"status":200,"resp_time":2.948198}
{"time":"October 29, 5:26 am","ts":1667001381,"status":200,"resp_time":2.955735}
{"time":"October 29, 7:24 am","ts":1667008478,"status":200,"resp_time":3.362552}
{"time":"October 29, 9:05 am","ts":1667014552,"status":200,"resp_time":2.837449}
{"time":"October 29, 9:49 am","ts":1667017155,"status":200,"resp_time":2.910421}
{"time":"October 29, 10:26 am","ts":1667019372,"status":200,"resp_time":3.196996}
{"time":"October 29, 10:53 am","ts":1667021036,"status":200,"resp_time":3.414334}
{"time":"October 29, 11:13 am","ts":1667022195,"status":200,"resp_time":2.968063}
{"time":"October 29, 11:25 am","ts":1667022935,"status":200,"resp_time":3.311768}
{"time":"October 29, 11:54 am","ts":1667024640,"status":200,"resp_time":2.991741}
{"time":"October 29, 12:18 pm","ts":1667026119,"status":200,"resp_time":3.184351}
{"time":"October 29, 12:29 pm","ts":1667026758,"status":200,"resp_time":3.238292}
{"time":"October 29, 12:53 pm","ts":1667028216,"status":200,"resp_time":2.917543}
{"time":"October 29, 1:08 pm","ts":1667029108,"status":200,"resp_time":3.14716}
{"time":"October 29, 1:18 pm","ts":1667029736,"status":200,"resp_time":3.046999}
{"time":"October 29, 1:29 pm","ts":1667030354,"status":200,"resp_time":3.041617}
{"time":"October 29, 2:02 pm","ts":1667032365,"status":200,"resp_time":2.888959}
{"time":"October 29, 2:22 pm","ts":1667033569,"status":200,"resp_time":3.311629}
{"time":"October 29, 2:47 pm","ts":1667035048,"status":200,"resp_time":2.938672}
{"time":"October 29, 3:05 pm","ts":1667036143,"status":200,"resp_time":3.298524}
{"time":"October 29, 3:17 pm","ts":1667036878,"status":200,"resp_time":3.162886}
{"time":"October 29, 3:28 pm","ts":1667037506,"status":200,"resp_time":3.194344}
