{"time":"October 10, 4:47 pm","ts":1665400674,"status":200,"resp_time":0.11138}
{"time":"October 10, 5:07 pm","ts":1665401879,"status":200,"resp_time":0.081525}
{"time":"October 10, 5:20 pm","ts":1665402653,"status":200,"resp_time":0.16089}
{"time":"October 10, 6:16 pm","ts":1665405986,"status":200,"resp_time":0.174704}
{"time":"October 10, 7:14 pm","ts":1665409494,"status":200,"resp_time":0.218853}
{"time":"October 10, 7:59 pm","ts":1665412173,"status":200,"resp_time":0.101487}
{"time":"October 10, 8:30 pm","ts":1665414052,"status":200,"resp_time":0.108196}
{"time":"October 10, 9:09 pm","ts":1665416349,"status":200,"resp_time":0.176166}
{"time":"October 10, 9:29 pm","ts":1665417591,"status":200,"resp_time":0.095213}
{"time":"October 10, 10:16 pm","ts":1665420377,"status":200,"resp_time":0.246269}
{"time":"October 10, 10:56 pm","ts":1665422818,"status":200,"resp_time":0.290805}
{"time":"October 10, 11:31 pm","ts":1665424896,"status":200,"resp_time":1.632185}
{"time":"October 11, 12:20 am","ts":1665427808,"status":200,"resp_time":0.250021}
{"time":"October 11, 12:45 am","ts":1665429349,"status":200,"resp_time":0.272173}
{"time":"October 11, 1:11 am","ts":1665430876,"status":200,"resp_time":0.189334}
{"time":"October 11, 1:26 am","ts":1665431785,"status":200,"resp_time":0.170867}
{"time":"October 11, 1:56 am","ts":1665433613,"status":200,"resp_time":0.234644}
{"time":"October 11, 2:19 am","ts":1665434962,"status":200,"resp_time":0.319946}
{"time":"October 11, 2:30 am","ts":1665435622,"status":200,"resp_time":0.237772}
{"time":"October 11, 3:01 am","ts":1665437476,"status":200,"resp_time":0.206181}
{"time":"October 11, 3:22 am","ts":1665438731,"status":200,"resp_time":0.19374}
{"time":"October 11, 3:51 am","ts":1665440508,"status":200,"resp_time":0.261512}
{"time":"October 11, 4:18 am","ts":1665442100,"status":200,"resp_time":0.317763}
{"time":"October 11, 4:29 am","ts":1665442771,"status":200,"resp_time":0.175381}
{"time":"October 11, 5:05 am","ts":1665444929,"status":200,"resp_time":0.107439}
{"time":"October 11, 5:27 am","ts":1665446243,"status":200,"resp_time":0.234383}
{"time":"October 11, 8:01 am","ts":1665455470,"status":200,"resp_time":0.10191}
{"time":"October 11, 9:56 am","ts":1665462377,"status":200,"resp_time":0.097625}
{"time":"October 11, 11:17 am","ts":1665467260,"status":200,"resp_time":0.07774}
{"time":"October 11, 12:00 pm","ts":1665469831,"status":200,"resp_time":0.204869}
{"time":"October 11, 12:52 pm","ts":1665472937,"status":200,"resp_time":0.092978}
{"time":"October 11, 1:30 pm","ts":1665475219,"status":200,"resp_time":0.183892}
{"time":"October 11, 2:15 pm","ts":1665477907,"status":200,"resp_time":0.106671}
{"time":"October 11, 2:40 pm","ts":1665479411,"status":200,"resp_time":0.08637}
{"time":"October 11, 3:14 pm","ts":1665481482,"status":200,"resp_time":3.593355}
{"time":"October 11, 3:29 pm","ts":1665482390,"status":200,"resp_time":0.318771}
{"time":"October 11, 4:03 pm","ts":1665484408,"status":200,"resp_time":0.060513}
{"time":"October 11, 4:25 pm","ts":1665485737,"status":200,"resp_time":0.25484}
{"time":"October 11, 4:48 pm","ts":1665487120,"status":200,"resp_time":0.169616}
{"time":"October 11, 5:08 pm","ts":1665488286,"status":200,"resp_time":0.191531}
{"time":"October 11, 5:21 pm","ts":1665489068,"status":200,"resp_time":0.103692}
{"time":"October 11, 6:12 pm","ts":1665492148,"status":200,"resp_time":0.179645}
{"time":"October 11, 7:12 pm","ts":1665495755,"status":200,"resp_time":0.05352}
{"time":"October 11, 7:51 pm","ts":1665498115,"status":200,"resp_time":0.161564}
{"time":"October 11, 8:23 pm","ts":1665499995,"status":200,"resp_time":0.270442}
{"time":"October 11, 8:53 pm","ts":1665501836,"status":200,"resp_time":0.229192}
{"time":"October 11, 9:22 pm","ts":1665503529,"status":200,"resp_time":0.0581}
{"time":"October 11, 10:01 pm","ts":1665505914,"status":200,"resp_time":0.056895}
{"time":"October 11, 10:44 pm","ts":1665508489,"status":200,"resp_time":0.084212}
{"time":"October 11, 11:18 pm","ts":1665510499,"status":200,"resp_time":0.086014}
{"time":"October 11, 11:39 pm","ts":1665511758,"status":200,"resp_time":0.173717}
{"time":"October 12, 12:17 am","ts":1665514026,"status":200,"resp_time":0.069789}
{"time":"October 12, 12:39 am","ts":1665515358,"status":200,"resp_time":0.085589}
{"time":"October 12, 1:03 am","ts":1665516792,"status":200,"resp_time":0.320157}
{"time":"October 12, 1:20 am","ts":1665517803,"status":200,"resp_time":0.319437}
{"time":"October 12, 1:30 am","ts":1665518434,"status":200,"resp_time":0.202968}
{"time":"October 12, 2:06 am","ts":1665520595,"status":200,"resp_time":0.062871}
{"time":"October 12, 2:26 am","ts":1665521780,"status":200,"resp_time":0.112034}
{"time":"October 12, 2:53 am","ts":1665523426,"status":200,"resp_time":0.210964}
{"time":"October 12, 3:16 am","ts":1665524815,"status":200,"resp_time":0.280079}
{"time":"October 12, 3:28 am","ts":1665525522,"status":200,"resp_time":0.391307}
{"time":"October 12, 4:00 am","ts":1665527456,"status":200,"resp_time":0.326537}
{"time":"October 12, 4:25 am","ts":1665528934,"status":200,"resp_time":0.075286}
{"time":"October 12, 4:57 am","ts":1665530833,"status":200,"resp_time":0.138213}
{"time":"October 12, 5:24 am","ts":1665532453,"status":200,"resp_time":0.231153}
{"time":"October 12, 7:40 am","ts":1665540608,"status":200,"resp_time":0.09562}
{"time":"October 12, 9:42 am","ts":1665547928,"status":200,"resp_time":0.131557}
{"time":"October 12, 10:54 am","ts":1665552282,"status":200,"resp_time":0.244358}
{"time":"October 12, 11:32 am","ts":1665554570,"status":200,"resp_time":0.268713}
{"time":"October 12, 12:19 pm","ts":1665557361,"status":200,"resp_time":0.190655}
{"time":"October 12, 12:46 pm","ts":1665559004,"status":200,"resp_time":0.320993}
{"time":"October 12, 1:15 pm","ts":1665560731,"status":200,"resp_time":0.095862}
{"time":"October 12, 1:29 pm","ts":1665561540,"status":200,"resp_time":0.325492}
{"time":"October 12, 2:06 pm","ts":1665563810,"status":200,"resp_time":0.101919}
{"time":"October 12, 2:30 pm","ts":1665565231,"status":200,"resp_time":0.249348}
{"time":"October 12, 3:07 pm","ts":1665567465,"status":200,"resp_time":0.273852}
{"time":"October 12, 3:28 pm","ts":1665568693,"status":200,"resp_time":0.13192}
{"time":"October 12, 4:03 pm","ts":1665570806,"status":200,"resp_time":0.074201}
{"time":"October 12, 4:27 pm","ts":1665572228,"status":200,"resp_time":0.252299}
{"time":"October 12, 4:54 pm","ts":1665573897,"status":200,"resp_time":0.369009}
{"time":"October 12, 5:13 pm","ts":1665575028,"status":200,"resp_time":0.162828}
{"time":"October 12, 5:26 pm","ts":1665575779,"status":200,"resp_time":0.103722}
{"time":"October 12, 6:19 pm","ts":1665578969,"status":200,"resp_time":0.1866}
{"time":"October 12, 7:12 pm","ts":1665582177,"status":200,"resp_time":0.066124}
{"time":"October 12, 7:58 pm","ts":1665584898,"status":200,"resp_time":0.258789}
{"time":"October 12, 8:28 pm","ts":1665586715,"status":200,"resp_time":0.174477}
{"time":"October 12, 9:05 pm","ts":1665588922,"status":200,"resp_time":0.175707}
{"time":"October 12, 9:31 pm","ts":1665590492,"status":200,"resp_time":0.116822}
{"time":"October 12, 10:30 pm","ts":1665594037,"status":200,"resp_time":0.192124}
{"time":"October 12, 11:22 pm","ts":1665597128,"status":200,"resp_time":0.19559}
{"time":"October 12, 11:59 pm","ts":1665599395,"status":200,"resp_time":0.159335}
